interactions/ext/paginator/__init__.py
interactions/ext/paginator/errors.py
interactions/ext/paginator/extension.py
interactions/ext/paginator/paginator.py
dinteractions_Paginator-2.0.2.dist-info/LICENSE
dinteractions_Paginator-2.0.2.dist-info/METADATA
dinteractions_Paginator-2.0.2.dist-info/WHEEL
dinteractions_Paginator-2.0.2.dist-info/top_level.txt
dinteractions_Paginator-2.0.2.dist-info/RECORD
