Metadata-Version: 2.1
Name: dinteractions-Paginator
Version: 2.0.2
Summary: Official interactions.py paginator
Home-page: https://github.com/Toricane/dinteractions-Paginator
Author: Toricane
Author-email: prjwl028@gmail.com
License: GNU
Classifier: Programming Language :: Python :: 3
Classifier: Development Status :: 5 - Production/Stable
Classifier: License :: OSI Approved :: GNU General Public License v3 (GPLv3)
Classifier: Operating System :: OS Independent
License-File: LICENSE
Requires-Dist: discord-py-interactions
Requires-Dist: interactions-wait-for
